{
    "name": "BC_3",
    "path": "/data/gcm49/experiment7/models/BC_3.h5",
    "train path": "/data/gcm49/experiment7/hdf5_files/BC_3.h5",
    "image height": 128,
    "image width": 128,
    "num channels": 1,
    "epochs": 50,
    "batch size": 16,
    "learning rate": 0.003,
    "logs": [
        {
            "epoch": 0,
            "loss": -0.4135109782218933,
            "val loss": -0.054790105670690536
        },
        {
            "epoch": 1,
            "loss": -0.5546776056289673,
            "val loss": -0.1263606995344162
        },
        {
            "epoch": 2,
            "loss": -0.6330333352088928,
            "val loss": -0.49517661333084106
        },
        {
            "epoch": 3,
            "loss": -0.6708629727363586,
            "val loss": -0.42169222235679626
        },
        {
            "epoch": 4,
            "loss": -0.7008722424507141,
            "val loss": -0.4808763563632965
        },
        {
            "epoch": 5,
            "loss": -0.7319628000259399,
            "val loss": -0.630541980266571
        },
        {
            "epoch": 6,
            "loss": -0.7335140705108643,
            "val loss": -0.5363706350326538
        },
        {
            "epoch": 7,
            "loss": -0.7534500360488892,
            "val loss": -0.3691767752170563
        },
        {
            "epoch": 8,
            "loss": -0.7514559030532837,
            "val loss": -0.6878689527511597
        },
        {
            "epoch": 9,
            "loss": -0.7730082273483276,
            "val loss": -0.5656810402870178
        },
        {
            "epoch": 10,
            "loss": -0.7801336646080017,
            "val loss": -0.5786341428756714
        },
        {
            "epoch": 11,
            "loss": -0.7804314494132996,
            "val loss": -0.6716199517250061
        },
        {
            "epoch": 12,
            "loss": -0.7849647998809814,
            "val loss": -0.6245307326316833
        },
        {
            "epoch": 13,
            "loss": -0.7917925119400024,
            "val loss": -0.5639727711677551
        },
        {
            "epoch": 14,
            "loss": -0.7920366525650024,
            "val loss": -0.6177824139595032
        },
        {
            "epoch": 15,
            "loss": -0.798395574092865,
            "val loss": -0.6806814670562744
        },
        {
            "epoch": 16,
            "loss": -0.7967026829719543,
            "val loss": -0.5654550790786743
        },
        {
            "epoch": 17,
            "loss": -0.8002663850784302,
            "val loss": -0.6849623918533325
        },
        {
            "epoch": 18,
            "loss": -0.8022353649139404,
            "val loss": -0.6081462502479553
        },
        {
            "epoch": 19,
            "loss": -0.8083034753799438,
            "val loss": -0.6366328597068787
        }
    ]
}